std_stream_cloner/__init__.py
std_stream_cloner/type.py
std_stream_cloner/version.py
std_stream_cloner-2024.5.dist-info/METADATA
std_stream_cloner-2024.5.dist-info/WHEEL
std_stream_cloner-2024.5.dist-info/top_level.txt
std_stream_cloner-2024.5.dist-info/RECORD
