Metadata-Version: 2.1
Name: std-stream-cloner
Version: 2024.5
Summary: Clones Standard Stream(s) to a (Log) File
Home-page: https://src.koda.cnrs.fr/eric.debreuve/std-stream-cloner/
Author: Eric Debreuve
Author-email: eric.debreuve@cnrs.fr
License: CeCILL-2.1
Project-URL: Documentation, https://src.koda.cnrs.fr/eric.debreuve/std-stream-cloner/-/wikis/home
Project-URL: Source, https://src.koda.cnrs.fr/eric.debreuve/std-stream-cloner/
Keywords: standard stream,stdout,stderr,log,file
Classifier: Topic :: Software Development
Classifier: Intended Audience :: Developers
Classifier: License :: OSI Approved :: CEA CNRS Inria Logiciel Libre License, version 2.1 (CeCILL-2.1)
Classifier: Programming Language :: Python :: 3
Classifier: Development Status :: 4 - Beta
Requires-Python: >=3.10
